{
  "livingroom/kodi": {
    "id": "livingroom/kodi",
    "type": "action.devices.types.TV",
    "disabled": false,
    "willReportState": true,
    "roomHint": "Living room",
    "name": {
      "defaultNames": [],
      "name": "Kodi",
      "nicknames": []
    },
    "deviceInfo": {
      "manufacturer": "openHome",
      "model": "0",
      "hwVersion": "0",
      "swVersion": "0"
    },
    "traits": [
      {
        "trait": "action.devices.traits.Modes",
        "attributes": {
          "availableModes": [
            {
              "name": "input source",
              "name_values": [
                {
                  "name_synonym": [
                    "activity"
                  ],
                  "lang": "en"
                }
              ],
              "settings": [
                {
                  "setting_name": "kodi",
                  "setting_values": [
                    {
                      "setting_synonym": [
                        "kodi",
                        "media centre"
                      ],
                      "lang": "en"
                    }
                  ]
                },
                {
                  "setting_name": "video player",
                  "setting_values": [
                    {
                      "setting_synonym": [
                        "video player",
                        "chromecast video"
                      ],
                      "lang": "en"
                    }
                  ]
                },
                {
                  "setting_name": "audio player",
                  "setting_values": [
                    {
                      "setting_synonym": [
                        "audio player",
                        "chromecast audio"
                      ],
                      "lang": "en"
                    }
                  ]
                }
              ],
              "ordered": false
            }
          ]
        },
        "commands": {
          "action.devices.commands.SetModes": {
            "updateModeSettings.input source": "livingroom/amplifier/mode/set"
          }
        },
        "state": {
          "currentModeSettings.input source": {
            "topic": "livingroom/amplifier/mode",
            "googleType": "string",
            "valueMap": [
              {
                "mqtt": "MPLAY",
                "type": "value",
                "google": "kodi"
              },
              {
                "mqtt": "BD",
                "type": "value",
                "google": "video player"
              },
              {
                "mqtt": "AUX1",
                "type": "value",
                "google": "audio player"
              },
              {
                "mqtt": "PowerOff",
                "type": "value",
                "google": "off"
              }
            ]
          }
        }
      },
      {
        "trait": "action.devices.traits.OnOff",
        "attributes": {},
        "commands": {
          "action.devices.commands.OnOff": {
            "on": "livingroom/tv/power/set"
          }
        },
        "state": {
          "on": {
            "topic": "livingroom/tv/power",
            "googleType": "bool",
            "valueMap": [
              {
                "mqtt": "ON",
                "type": "value",
                "google": true
              },
              {
                "mqtt": "OFF",
                "type": "value",
                "google": false
              }
            ]
          }
        }
      },
      {
        "trait": "action.devices.traits.Volume",
        "attributes": {
          "volumeMaxLevel": 70,
          "volumeCanMuteAndUnmute": true,
          "volumeDefaultPercentage": 30,
          "levelStepSize": 1
        },
        "commands": {
          "action.devices.commands.setVolume": {
            "volumeLevel": "livingroom/amplifier/volume/set"
          },
          "action.devices.commands.mute": {
            "mute": "livingroom/amplifier/mute/set"
          },
          "action.devices.commands.volumeRelative": {
            "relativeSteps": "livingroom/amplifier/relativeVolume/set"
          }
        },
        "state": {
          "currentVolume": {
            "topic": "livingroom/amplifier/volume",
            "googleType": "numeric",
            "valueMap": null
          },
          "isMuted": {
            "topic": "livingroom/amplifier/mute",
            "googleType": "bool",
            "valueMap": [
              {
                "mqtt": "ON",
                "type": "value",
                "google": true
              },
              {
                "mqtt": "OFF",
                "type": "value",
                "google": false
              }
            ]
          }
        }
      },
      {
        "trait": "action.devices.traits.Channel",
        "attributes": {
          "availableChannels": [
            {
              "key": "1438667575",
              "names": [
                "animal planet"
              ],
              "number": "103"
            },
            {
              "key": "1023136028",
              "names": [
                "bbc brit"
              ],
              "number": "75"
            },
            {
              "key": "980480405",
              "names": [
                "boomerang"
              ],
              "number": "71"
            },
            {
              "key": "1502793520",
              "names": [
                "c more first"
              ],
              "number": "108"
            },
            {
              "key": "467888432",
              "names": [
                "c more hits"
              ],
              "number": "26"
            },
            {
              "key": "1934503478",
              "names": [
                "c more series"
              ],
              "number": "128"
            },
            {
              "key": "562464304",
              "names": [
                "c more stars"
              ],
              "number": "35"
            },
            {
              "key": "907730525",
              "names": [
                "cartoon network"
              ],
              "number": "67"
            },
            {
              "key": "1655343506",
              "names": [
                "discovery investigation"
              ],
              "number": "118"
            },
            {
              "key": "2079508751",
              "names": [
                "discovery science"
              ],
              "number": "137"
            },
            {
              "key": "574736160",
              "names": [
                "discovery world"
              ],
              "number": "38"
            },
            {
              "key": "285845979",
              "names": [
                "disney channel"
              ],
              "number": "13"
            },
            {
              "key": "2113043720",
              "names": [
                "disney junior"
              ],
              "number": "139"
            },
            {
              "key": "989016137",
              "names": [
                "disney xd"
              ],
              "number": "72"
            },
            {
              "key": "696621802",
              "names": [
                "eurosport 1"
              ],
              "number": "54"
            },
            {
              "key": "1533468104",
              "names": [
                "eurosport norge",
                "eurosport norway",
                "eurosport"
              ],
              "number": "110"
            },
            {
              "key": "1448810508",
              "names": [
                "eurosport pluss 1"
              ],
              "number": "105"
            },
            {
              "key": "1396657298",
              "names": [
                "eurosport pluss 10"
              ],
              "number": "100"
            },
            {
              "key": "404636173",
              "names": [
                "eurosport pluss 11"
              ],
              "number": "20"
            },
            {
              "key": "106157846",
              "names": [
                "eurosport pluss 12"
              ],
              "number": "5"
            },
            {
              "key": "2092257178",
              "names": [
                "eurosport pluss 2"
              ],
              "number": "138"
            },
            {
              "key": "694881630",
              "names": [
                "eurosport pluss 3"
              ],
              "number": "53"
            },
            {
              "key": "2050089414",
              "names": [
                "eurosport pluss 4"
              ],
              "number": "136"
            },
            {
              "key": "1553398173",
              "names": [
                "eurosport pluss 5"
              ],
              "number": "114"
            },
            {
              "key": "718229927",
              "names": [
                "eurosport pluss 6"
              ],
              "number": "55"
            },
            {
              "key": "354259153",
              "names": [
                "eurosport pluss 7"
              ],
              "number": "18"
            },
            {
              "key": "1438857638",
              "names": [
                "eurosport pluss 8"
              ],
              "number": "104"
            },
            {
              "key": "581481051",
              "names": [
                "eurosport pluss 9"
              ],
              "number": "40"
            },
            {
              "key": "754151151",
              "names": [
                "fem"
              ],
              "number": "58"
            },
            {
              "key": "564158804",
              "names": [
                "fox norge"
              ],
              "number": "36"
            },
            {
              "key": "567594713",
              "names": [
                "fatsone"
              ],
              "number": "37"
            },
            {
              "key": "2117770762",
              "names": [
                "h2",
                "history 2"
              ],
              "number": "140"
            },
            {
              "key": "497741484",
              "names": [
                "history"
              ],
              "number": "29"
            },
            {
              "key": "480724960",
              "names": [
                "mtv norge",
                "mtv norway"
              ],
              "number": "27"
            },
            {
              "key": "1545647773",
              "names": [
                "matkanalen",
                "food channel"
              ],
              "number": "113"
            },
            {
              "key": "687660205",
              "names": [
                "max"
              ],
              "number": "51"
            },
            {
              "key": "1211289342",
              "names": [
                "nrk 1",
                "nrk"
              ],
              "number": "88"
            },
            {
              "key": "719420171",
              "names": [
                "nrk 2"
              ],
              "number": "56"
            },
            {
              "key": "451480675",
              "names": [
                "nrk 3"
              ],
              "number": "24"
            },
            {
              "key": "2005589667",
              "names": [
                "nat geo wild",
                "wild",
                "national geographic wild"
              ],
              "number": "132"
            },
            {
              "key": "1568842617",
              "names": [
                "national geo norge",
                "national geo norway",
                "nat geo norway",
                "national geographic norway"
              ],
              "number": "116"
            },
            {
              "key": "264399957",
              "names": [
                "nick jr",
                "nick junior"
              ],
              "number": "12"
            },
            {
              "key": "1330275784",
              "names": [
                "nickelodeon"
              ],
              "number": "98"
            },
            {
              "key": "523616644",
              "names": [
                "nicktoons"
              ],
              "number": "31"
            },
            {
              "key": "173893257",
              "names": [
                "strive sport 1"
              ],
              "number": "7"
            },
            {
              "key": "1639750323",
              "names": [
                "strive sport 2"
              ],
              "number": "117"
            },
            {
              "key": "1425135611",
              "names": [
                "tlc norge",
                "tlc norway",
                "tlc"
              ],
              "number": "102"
            },
            {
              "key": "618349593",
              "names": [
                "tv 2",
                "tv2"
              ],
              "number": "45"
            },
            {
              "key": "76010936",
              "names": [
                "tv 2 nyhetskanalen",
                "tv 2 news"
              ],
              "number": "3"
            },
            {
              "key": "604570378",
              "names": [
                "tv norge",
                "tv norway"
              ],
              "number": "43"
            },
            {
              "key": "1909223920",
              "names": [
                "tv 2 livsstil",
                "tv 2 lifestyle"
              ],
              "number": "127"
            },
            {
              "key": "692601560",
              "names": [
                "tv2 sport 1"
              ],
              "number": "52"
            },
            {
              "key": "1415872412",
              "names": [
                "tv2 sport 2"
              ],
              "number": "101"
            },
            {
              "key": "306307378",
              "names": [
                "tv 2 sport premium"
              ],
              "number": "15"
            },
            {
              "key": "427707336",
              "names": [
                "tv 2 sport premium 2"
              ],
              "number": "22"
            },
            {
              "key": "2122895646",
              "names": [
                "tv 2 zebra",
                "zebra"
              ],
              "number": "141"
            },
            {
              "key": "1182065905",
              "names": [
                "tv 3"
              ],
              "number": "85"
            },
            {
              "key": "539157922",
              "names": [
                "tv 6"
              ],
              "number": "34"
            },
            {
              "key": "1490501170",
              "names": [
                "v film action",
                "film action"
              ],
              "number": "106"
            },
            {
              "key": "1498716624",
              "names": [
                "v film family",
                "film family"
              ],
              "number": "107"
            },
            {
              "key": "588099698",
              "names": [
                "v film hits",
                "film hits"
              ],
              "number": "42"
            },
            {
              "key": "836590138",
              "names": [
                "v film premiere",
                "film premier"
              ],
              "number": "63"
            },
            {
              "key": "1562566035",
              "names": [
                "v series"
              ],
              "number": "115"
            },
            {
              "key": "1782099190",
              "names": [
                "sport +",
                "sport pluss"
              ],
              "number": "122"
            },
            {
              "key": "350596003",
              "names": [
                "v sport 1",
                "sport 1"
              ],
              "number": "17"
            },
            {
              "key": "1545394494",
              "names": [
                "v sport 2",
                "sport 2"
              ],
              "number": "112"
            },
            {
              "key": "666195037",
              "names": [
                "v sport 3",
                "sport 3"
              ],
              "number": "50"
            },
            {
              "key": "851713527",
              "names": [
                "vox"
              ],
              "number": "64"
            },
            {
              "key": "664914669",
              "names": [
                "viasat 4"
              ],
              "number": "49"
            },
            {
              "key": "182499844",
              "names": [
                "actionmax",
                "action max"
              ],
              "number": "8"
            },
            {
              "key": "1206374543",
              "names": [
                "cinemax"
              ],
              "number": "87"
            },
            {
              "key": "455606633",
              "names": [
                "moremax",
                "more max"
              ],
              "number": "25"
            },
            {
              "key": "582101227",
              "names": [
                "thrillermax"
              ],
              "number": "41"
            },
            {
              "key": "1276749784",
              "names": [
                "epix"
              ],
              "number": "93"
            },
            {
              "key": "532504293",
              "names": [
                "epix hits"
              ],
              "number": "32"
            },
            {
              "key": "1890860502",
              "names": [
                "epix drive"
              ],
              "number": "126"
            },
            {
              "key": "488857645",
              "names": [
                "fox sports 1"
              ],
              "number": "28"
            },
            {
              "key": "1961395563",
              "names": [
                "fox sports 2"
              ],
              "number": "131"
            },
            {
              "key": "576168673",
              "names": [
                "hbo comedy"
              ],
              "number": "39"
            },
            {
              "key": "861039717",
              "names": [
                "hbo family"
              ],
              "number": "65"
            },
            {
              "key": "611920727",
              "names": [
                "hbo"
              ],
              "number": "44"
            },
            {
              "key": "1129587830",
              "names": [
                "hbo signature"
              ],
              "number": "83"
            },
            {
              "key": "1130731005",
              "names": [
                "hbo zone"
              ],
              "number": "84"
            },
            {
              "key": "1796255320",
              "names": [
                "moviemax"
              ],
              "number": "124"
            },
            {
              "key": "183081609",
              "names": [
                "outermax"
              ],
              "number": "9"
            },
            {
              "key": "1283971627",
              "names": [
                "showtime beyond"
              ],
              "number": "94"
            },
            {
              "key": "1027362976",
              "names": [
                "showtime extreme"
              ],
              "number": "76"
            },
            {
              "key": "878243499",
              "names": [
                "showtime"
              ],
              "number": "66"
            },
            {
              "key": "401331941",
              "names": [
                "showtime women"
              ],
              "number": "19"
            },
            {
              "key": "1737763935",
              "names": [
                "starz comedy"
              ],
              "number": "121"
            },
            {
              "key": "2028353636",
              "names": [
                "starz"
              ],
              "number": "134"
            },
            {
              "key": "1248656958",
              "names": [
                "starz edge"
              ],
              "number": "91"
            },
            {
              "key": "1276731627",
              "names": [
                "starz encore"
              ],
              "number": "92"
            },
            {
              "key": "2029791178",
              "names": [
                "true movies"
              ],
              "number": "142"
            },
            {
              "key": "1213409018",
              "names": [
                "sky cinema premiere"
              ],
              "number": "89"
            },
            {
              "key": "990540802",
              "names": [
                "sky cinema action"
              ],
              "number": "73"
            },
            {
              "key": "807934709",
              "names": [
                "sky cinema select"
              ],
              "number": "60"
            },
            {
              "key": "1309216273",
              "names": [
                "sky cinema drama"
              ],
              "number": "96"
            },
            {
              "key": "23844753",
              "names": [
                "sky cinema greats"
              ],
              "number": "1"
            },
            {
              "key": "1011326921",
              "names": [
                "sky cinema disney"
              ],
              "number": "74"
            },
            {
              "key": "627911540",
              "names": [
                "sky cinema comedy",
                "cinema comedy",
                "sky comedy"
              ],
              "number": "46"
            },
            {
              "key": "1088474444",
              "names": [
                "sky cinema thriller"
              ],
              "number": "81"
            },
            {
              "key": "1835058443",
              "names": [
                "bt sport 1"
              ],
              "number": "125"
            },
            {
              "key": "644912628",
              "names": [
                "bt sport 2"
              ],
              "number": "47"
            },
            {
              "key": "821794193",
              "names": [
                "bt sport 3"
              ],
              "number": "61"
            },
            {
              "key": "1938534685",
              "names": [
                "bt sport espn"
              ],
              "number": "129"
            },
            {
              "key": "2121061257",
              "names": [
                "bbc world news"
              ],
              "number": "153"
            },
            {
              "key": "916649053",
              "names": [
                "box nation",
                "boxnation",
                "boxing"
              ],
              "number": "68"
            },
            {
              "key": "1543479827",
              "names": [
                "dmax",
                "d max"
              ],
              "number": "143"
            },
            {
              "key": "44095467",
              "names": [
                "mtv live"
              ],
              "number": "144"
            },
            {
              "key": "1280854010",
              "names": [
                "mtv"
              ],
              "number": "145"
            },
            {
              "key": "1734151200",
              "names": [
                "mtv base"
              ],
              "number": "151"
            },
            {
              "key": "1101967932",
              "names": [
                "mtv classic"
              ],
              "number": "149"
            },
            {
              "key": "2118552641",
              "names": [
                "mtv hits"
              ],
              "number": "152"
            },
            {
              "key": "65020211",
              "names": [
                "mtv dance"
              ],
              "number": "146"
            },
            {
              "key": "762766415",
              "names": [
                "mtv omg"
              ],
              "number": "148"
            },
            {
              "key": "1623259698",
              "names": [
                "mtv music"
              ],
              "number": "150"
            },
            {
              "key": "657525171",
              "names": [
                "mtv rocks"
              ],
              "number": "147"
            },
            {
              "key": "781510642",
              "names": [
                "sky cinema family"
              ],
              "number": "59"
            },
            {
              "key": "1072838650",
              "names": [
                "sky cinema sci-fi and horror"
              ],
              "number": "79"
            },
            {
              "key": "1794893668",
              "names": [
                "sky cinema hits"
              ],
              "number": "123"
            },
            {
              "key": "432849826",
              "names": [
                "showtime showcase"
              ],
              "number": "23"
            },
            {
              "key": "1544596910",
              "names": [
                "showtime next"
              ],
              "number": "111"
            },
            {
              "key": "503147869",
              "names": [
                "showtime 2"
              ],
              "number": "30"
            },
            {
              "key": "1394255849",
              "names": [
                "starz cinema"
              ],
              "number": "99"
            },
            {
              "key": "347292021",
              "names": [
                "indie"
              ],
              "number": "16"
            },
            {
              "key": "535959370",
              "names": [
                "alternative"
              ],
              "number": "33"
            },
            {
              "key": "95114608",
              "names": [
                "brits plus hits"
              ],
              "number": "4"
            },
            {
              "key": "1314934902",
              "names": [
                "country"
              ],
              "number": "97"
            },
            {
              "key": "928019937",
              "names": [
                "dance"
              ],
              "number": "69"
            },
            {
              "key": "294516655",
              "names": [
                "hip hop and r&b",
                "hip hop and r and b"
              ],
              "number": "14"
            },
            {
              "key": "1114779113",
              "names": [
                "hit list"
              ],
              "number": "82"
            },
            {
              "key": "1948285729",
              "names": [
                "holidays yule logs"
              ],
              "number": "130"
            },
            {
              "key": "1189347038",
              "names": [
                "kidz only"
              ],
              "number": "86"
            },
            {
              "key": "1070999906",
              "names": [
                "metal"
              ],
              "number": "78"
            },
            {
              "key": "656461479",
              "names": [
                "mexicana"
              ],
              "number": "48"
            },
            {
              "key": "974310994",
              "names": [
                "musica urbana"
              ],
              "number": "70"
            },
            {
              "key": "64935574",
              "names": [
                "pop and country"
              ],
              "number": "2"
            },
            {
              "key": "1717745721",
              "names": [
                "pop hits"
              ],
              "number": "120"
            },
            {
              "key": "1086214056",
              "names": [
                "pop latino"
              ],
              "number": "80"
            },
            {
              "key": "2012035546",
              "names": [
                "r&b soul",
                "r and b soul"
              ],
              "number": "133"
            },
            {
              "key": "1509480077",
              "names": [
                "rap"
              ],
              "number": "109"
            },
            {
              "key": "421090881",
              "names": [
                "rock"
              ],
              "number": "21"
            },
            {
              "key": "2043533798",
              "names": [
                "teen beats"
              ],
              "number": "135"
            },
            {
              "key": "240040125",
              "names": [
                "toddler tunes"
              ],
              "number": "10"
            },
            {
              "key": "1218264040",
              "names": [
                "tropicales"
              ],
              "number": "90"
            },
            {
              "key": "252178821",
              "names": [
                "trowback jamz"
              ],
              "number": "11"
            },
            {
              "key": "823974128",
              "names": [
                "y2k"
              ],
              "number": "62"
            }
          ]
        },
        "commands": {
          "action.devices.commands.selectChannel": {
            "channelNumber": "livingroom/kodi/channel/set"
          },
          "action.devices.commands.returnChannel": {
            "_": "livingroom/kodi/returnChannel/set"
          },
          "action.devices.commands.relativeChannel": {
            "relativeChannelChange": "livingroom/kodi/relativeChannel/set"
          }
        },
        "state": {
          "channelNumber": {
            "topic": "livingroom/kodi/channel",
            "googleType": "numeric",
            "valueMap": null
          }
        }
      },
      {
        "trait": "action.devices.traits.MediaState",
        "attributes": {
          "supportActivityState": true,
          "supportPlaybackState": true
        },
        "commands": {},
        "state": {
          "activityState": {
            "topic": "livingroom/kodi/activityState",
            "googleType": "string",
            "valueMap": []
          },
          "playbackState": {
            "topic": "livingroom/kodi/playbackState",
            "googleType": "string",
            "valueMap": []
          }
        }
      },
      {
        "trait": "action.devices.traits.AppSelector",
        "attributes": {
          "availableApplications": [
            {
              "key": "youtube",
              "names": [
                {
                  "name_synonym": [
                    "youtube",
                    "tube"
                  ],
                  "lang": "en"
                }
              ]
            },
            {
              "key": "movies",
              "names": [
                {
                  "name_synonym": [
                    "film",
                    "movies"
                  ],
                  "lang": "en"
                }
              ]
            },
            {
              "key": "tv",
              "names": [
                {
                  "name_synonym": [
                    "television",
                    "show",
                    "shows",
                    "tv shows"
                  ],
                  "lang": "en"
                }
              ]
            },
            {
              "key": "spotify",
              "names": [
                {
                  "name_synonym": [
                    "music"
                  ],
                  "lang": "en"
                }
              ]
            }
          ]
        },
        "commands": {
          "action.devices.commands.appSelect": {
            "newApplication": "livingroom/kodi/app/set"
          }
        },
        "state": {
          "currentApplication": {
            "topic": "livingroom/kodi/app",
            "googleType": "string",
            "valueMap": []
          }
        }
      },
      {
        "trait": "action.devices.traits.TransportControl",
        "attributes": {
          "transportControlSupportedCommands": [
            "NEXT",
            "PREVIOUS",
            "PAUSE",
            "STOP",
            "RESUME",
            "CAPTION_CONTROL"
          ]
        },
        "commands": {
          "action.devices.commands.mediaClosedCaptioningOff": {
            "_": "livingroom/kodi/captioningOff/set"
          },
          "action.devices.commands.mediaNext": {
            "_": "livingroom/kodi/mediaNext/set"
          },
          "action.devices.commands.mediaPrevious": {
            "_": "livingroom/kodi/mediaPrevious/set"
          },
          "action.devices.commands.mediaResume": {
            "_": "livingroom/kodi/mediaResume/set"
          },
          "action.devices.commands.mediaPause": {
            "_": "livingroom/kodi/mediaPause/set"
          },
          "action.devices.commands.mediaStop": {
            "_": "livingroom/kodi/mediaStop/set"
          },
          "action.devices.commands.mediaSeekToPosition": {
            "absPositionMs": "livingroom/kodi/absPositionMs/set"
          }
        },
        "state": {}
      }
    ],
    "customData": null
  },
  "livingroom/balconyDoor": {
    "id": "livingroom/balconyDoor",
    "type": "action.devices.types.DOOR",
    "disabled": false,
    "willReportState": true,
    "roomHint": "Living room",
    "name": {
      "defaultNames": [],
      "name": "Balcony door",
      "nicknames": []
    },
    "deviceInfo": null,
    "traits": [
      {
        "trait": "action.devices.traits.OpenClose",
        "attributes": {
          "openDirection": [
            "LEFT",
            "RIGHT"
          ],
          "discreteOnlyOpenClose": true,
          "queryOnlyOpenClose": true
        },
        "commands": {},
        "state": {
          "openPercent": {
            "topic": "livingroom/balconyDoor/status",
            "googleType": "numeric",
            "valueMap": [
              {
                "mqtt": "OPEN",
                "type": "value",
                "google": 100
              },
              {
                "mqtt": "CLOSED",
                "type": "value",
                "google": 0
              }
            ]
          }
        }
      }
    ],
    "customData": null
  },
  "bedroom/vacuumCleaner": {
    "id": "bedroom/vacuumCleaner",
    "type": "action.devices.types.VACUUM",
    "disabled": false,
    "willReportState": true,
    "roomHint": "Bedroom",
    "name": {
      "defaultNames": [],
      "name": "Vacuum cleaner",
      "nicknames": []
    },
    "deviceInfo": {
      "manufacturer": "Some Company",
      "model": "Some Model",
      "hwVersion": "1.0",
      "swVersion": "1.0"
    },
    "traits": [
      {
        "trait": "action.devices.traits.StartStop",
        "attributes": {
          "pausable": false
        },
        "commands": {
          "action.devices.commands.StartStop": {
            "start": "bedroom/vacuum/clean/set"
          }
        },
        "state": {
          "isRunning": {
            "topic": "bedroom/vacuum/docked",
            "googleType": "bool",
            "valueMap": null
          },
          "isPaused": {
            "topic": null,
            "googleType": "bool",
            "valueMap": null
          }
        }
      }
    ],
    "customData": null
  },
  "other/camera/danmarksplass": {
    "id": "other/camera/danmarksplass",
    "type": "action.devices.types.CAMERA",
    "disabled": false,
    "willReportState": true,
    "roomHint": "Others",
    "name": {
      "defaultNames": [],
      "name": "Danmarksplass",
      "nicknames": []
    },
    "deviceInfo": {
      "manufacturer": "Some Company",
      "model": "Some Model",
      "hwVersion": "1.0",
      "swVersion": "1.0"
    },
    "traits": [
      {
        "trait": "action.devices.traits.CameraStream",
        "attributes": {
          "cameraStreamSupportedProtocols": [
            "hls"
          ],
          "cameraStreamNeedAuthToken": false,
          "cameraStreamNeedDrmEncryption": false
        },
        "commands": {
          "action.devices.commands.GetCameraStream": {}
        },
        "state": {
          "cameraStreamAccessUrl": {
            "topic": null,
            "googleType": "string",
            "valueMap": [
              {
                "type": "static",
                "google": "https://stream1.vossaskyen.no/bt/Danmarksplass.stream/playlist.m3u8"
              }
            ]
          },
          "cameraStreamReceiverAppId": {
            "topic": null,
            "googleType": "string",
            "valueMap": [
              {
                "type": "static",
                "google": null
              }
            ]
          },
          "cameraStreamAuthToken": {
            "topic": null,
            "googleType": "string",
            "valueMap": [
              {
                "type": "static",
                "google": null
              }
            ]
          }
        }
      }
    ],
    "customData": null
  },
  "bedroom/thermostat": {
    "id": "bedroom/thermostat",
    "type": "action.devices.types.THERMOSTAT",
    "disabled": false,
    "willReportState": true,
    "roomHint": "Bedroom",
    "name": {
      "defaultNames": [],
      "name": "Thermostat [Bedroom]",
      "nicknames": []
    },
    "deviceInfo": {
      "manufacturer": "openHome",
      "model": "0.1",
      "hwVersion": "0.1",
      "swVersion": "0.1"
    },
    "traits": [
      {
        "trait": "action.devices.traits.TemperatureSetting",
        "attributes": {
          "availableThermostatModes": "off,heat,cool,on,heatcool,auto,fan-only,purifier,eco,dry",
          "thermostatTemperatureUnit": "C"
        },
        "commands": {
          "action.devices.commands.ThermostatTemperatureSetpoint": {
            "thermostatTemperatureSetpoint": "bedroom/thermostat/thermostatTemperatureSetpoint/set"
          },
          "action.devices.commands.ThermostatTemperatureSetRange": {
            "thermostatTemperatureSetpointHigh": "bedroom/thermostat/thermostatTemperatureSetpointHigh/set",
            "thermostatTemperatureSetpointLow": "bedroom/thermostat/thermostatTemperatureSetpointLow/set"
          },
          "action.devices.commands.ThermostatSetMode": {
            "thermostatMode": "bedroom/thermostat/thermostatMode/set"
          },
          "action.devices.commands.TemperatureRelative": {
            "thermostatTemperatureRelativeDegree": "bedroom/thermostat/thermostatTemperatureRelativeDegree/set",
            "thermostatTemperatureRelativeWeight": "bedroom/thermostat/thermostatTemperatureRelativeWeight/set"
          }
        },
        "state": {
          "thermostatMode": {
            "topic": "bedroom/thermostat/thermostatMode",
            "googleType": "string",
            "valueMap": []
          },
          "thermostatTemperatureSetpoint": {
            "topic": "bedroom/thermostat/thermostatTemperatureSetpoint",
            "googleType": "numeric",
            "valueMap": null
          },
          "thermostatTemperatureAmbient": {
            "topic": "bedroom/thermostat/thermostatTemperatureAmbient",
            "googleType": "numeric",
            "valueMap": null
          },
          "thermostatTemperatureSetpointHigh": {
            "topic": "bedroom/thermostat/thermostatTemperatureSetpointHigh",
            "googleType": "numeric",
            "valueMap": null
          },
          "thermostatTemperatureSetpointLow": {
            "topic": "bedroom/thermostat/thermostatTemperatureSetpointLow",
            "googleType": "numeric",
            "valueMap": null
          },
          "thermostatHumidityAmbient": {
            "topic": "bedroom/thermostat/thermostatHumidityAmbient",
            "googleType": "numeric",
            "valueMap": null
          }
        }
      }
    ],
    "customData": null
  },
  "bedroom/bedroomDoor": {
    "id": "bedroom/bedroomDoor",
    "type": "action.devices.types.DOOR",
    "disabled": false,
    "willReportState": true,
    "roomHint": "Bedroom",
    "name": {
      "defaultNames": [],
      "name": "Bedroom door",
      "nicknames": []
    },
    "deviceInfo": null,
    "traits": [
      {
        "trait": "action.devices.traits.OpenClose",
        "attributes": {
          "openDirection": [
            "LEFT",
            "RIGHT"
          ],
          "discreteOnlyOpenClose": true,
          "queryOnlyOpenClose": true
        },
        "commands": {},
        "state": {
          "openPercent": {
            "topic": "bedroom/bedroomDoor/status",
            "googleType": "numeric",
            "valueMap": [
              {
                "mqtt": "OPEN",
                "type": "value",
                "google": 100
              },
              {
                "mqtt": "CLOSED",
                "type": "value",
                "google": 0
              }
            ]
          }
        }
      }
    ],
    "customData": null
  },
  "livingroom/airPurifier": {
    "id": "livingroom/airPurifier",
    "type": "action.devices.types.AIRPURIFIER",
    "disabled": false,
    "willReportState": true,
    "roomHint": "Bedroom",
    "name": {
      "defaultNames": [],
      "name": "DIY",
      "nicknames": []
    },
    "deviceInfo": null,
    "traits": [
      {
        "trait": "action.devices.traits.OnOff",
        "attributes": {},
        "commands": {
          "action.devices.commands.OnOff": {
            "on": "livingroom/airPurifier/power/set"
          }
        },
        "state": {
          "on": {
            "topic": "livingroom/airPurifier/power",
            "googleType": "bool",
            "valueMap": [
              {
                "mqtt": "ON",
                "type": "value",
                "google": true
              },
              {
                "mqtt": "OFF",
                "type": "value",
                "google": false
              }
            ]
          }
        }
      },
      {
        "trait": "action.devices.traits.SensorState",
        "attributes": {
          "sensorStatesSupported": [
            {
              "name": "AirQuality",
              "descriptiveCapabilities": {
                "availableStates": [
                  "healthy",
                  "moderate",
                  "unhealthy",
                  "very unhealthy"
                ]
              }
            },
            {
              "name": "HEPAFilterLifeTime",
              "numericCapabilities": {
                "rawValueUnit": "PERCENTAGE"
              }
            }
          ]
        },
        "commands": {},
        "state": {
          "currentSensorStateData.[0].name": {
            "topic": null,
            "googleType": "string",
            "valueMap": [
              {
                "type": "static",
                "google": "AirQuality"
              }
            ]
          },
          "currentSensorStateData.[1].name": {
            "topic": null,
            "googleType": "string",
            "valueMap": [
              {
                "type": "static",
                "google": "HEPAFilterLifeTime"
              }
            ]
          },
          "currentSensorStateData.[0].currentSensorState": {
            "topic": "livingroom/airPurifier/sensorState",
            "googleType": "string",
            "valueMap": []
          },
          "currentSensorStateData.[1].currentSensorState": {
            "topic": "livingroom/airPurifier/sensorState2",
            "googleType": "numeric",
            "valueMap": null
          }
        }
      },
      {
        "trait": "action.devices.traits.FanSpeed",
        "attributes": {
          "availableFanSpeeds": {
            "speeds": [
              {
                "speed_name": "Low",
                "speed_values": [
                  {
                    "speed_synonym": [
                      "low"
                    ],
                    "lang": "en"
                  }
                ]
              },
              {
                "speed_name": "Medium",
                "speed_values": [
                  {
                    "speed_synonym": [
                      "medium"
                    ],
                    "lang": "en"
                  }
                ]
              },
              {
                "speed_name": "High",
                "speed_values": [
                  {
                    "speed_synonym": [
                      "high"
                    ],
                    "lang": "en"
                  }
                ]
              }
            ],
            "ordered": true
          },
          "reversible": false
        },
        "commands": {
          "action.devices.commands.SetFanSpeed": {
            "fanSpeed": "livingroom/airPurifier/fanSpeed/set"
          }
        },
        "state": {
          "currentFanSpeedSetting": {
            "topic": "livingroom/airPurifier/fanSpeed",
            "googleType": "string",
            "valueMap": [
              {
                "mqtt": "1",
                "type": "value",
                "google": "Low"
              },
              {
                "mqtt": "5",
                "type": "value",
                "google": "Medium"
              },
              {
                "mqtt": "10",
                "type": "value",
                "google": "High"
              }
            ]
          }
        }
      },
      {
        "trait": "action.devices.traits.Modes",
        "attributes": {
          "availableModes": [
            {
              "name": "input source",
              "name_values": [
                {
                  "name_synonym": [
                    "activity"
                  ],
                  "lang": "en"
                }
              ],
              "settings": [
                {
                  "setting_name": "tv",
                  "setting_values": [
                    {
                      "setting_synonym": [
                        "tv",
                        "television"
                      ],
                      "lang": "en"
                    }
                  ]
                },
                {
                  "setting_name": "meda player",
                  "setting_values": [
                    {
                      "setting_synonym": [
                        "chromecast"
                      ],
                      "lang": "en"
                    }
                  ]
                }
              ],
              "ordered": false
            }
          ]
        },
        "commands": {
          "action.devices.commands.SetModes": {
            "updateModeSettings.input source": "MQTT_COMMAND_TOPIC"
          }
        },
        "state": {
          "currentModeSettings.input source": {
            "topic": "MQTT_STATE_TOPIC",
            "googleType": "string",
            "valueMap": [
              {
                "mqtt": "Watch TV",
                "type": "value",
                "google": "tv"
              },
              {
                "mqtt": "Watch Chromecast",
                "type": "value",
                "google": "media player"
              },
              {
                "mqtt": "Watch Roku",
                "type": "value",
                "google": "game console"
              },
              {
                "mqtt": "PowerOff",
                "type": "value",
                "google": "off"
              }
            ]
          }
        }
      }
    ],
    "customData": null
  },
  "bedroom/smokeDetector": {
    "id": "bedroom/smokeDetector",
    "type": "action.devices.types.SMOKE_DETECTOR",
    "disabled": false,
    "willReportState": true,
    "roomHint": "Bedroom",
    "name": {
      "defaultNames": [],
      "name": "Smoke detector",
      "nicknames": []
    },
    "deviceInfo": null,
    "traits": [
      {
        "trait": "action.devices.traits.SensorState",
        "attributes": {
          "sensorStatesSupported": [
            {
              "name": "SmokeLevel",
              "numericCapabilities": {
                "rawValueUnit": "PARTS_PER_MILLION"
              },
              "descriptiveCapabilities": {
                "availableStates": [
                  "smoke detected",
                  "no smoke detected"
                ]
              }
            }
          ]
        },
        "commands": {},
        "state": {
          "currentSensorStateData.[0].name": {
            "topic": null,
            "googleType": "string",
            "valueMap": [
              {
                "type": "static",
                "google": "SmokeLevel"
              }
            ]
          },
          "currentSensorStateData.[0].currentSensorState": {
            "topic": "bedroom/smokeDetector/sensorState",
            "googleType": "string",
            "valueMap": []
          }
        }
      }
    ],
    "customData": null
  },
  "livingroom/buttShaker": {
    "id": "livingroom/buttShaker",
    "type": "action.devices.types.SPEAKER",
    "disabled": false,
    "willReportState": true,
    "roomHint": "Living room",
    "name": {
      "defaultNames": [],
      "name": "Buttshaker",
      "nicknames": []
    },
    "deviceInfo": null,
    "traits": [
      {
        "trait": "action.devices.traits.OnOff",
        "attributes": {},
        "commands": {
          "action.devices.commands.OnOff": {
            "on": "livingroom/buttShaker/power/set"
          }
        },
        "state": {
          "on": {
            "topic": "livingroom/buttShaker/power",
            "googleType": "bool",
            "valueMap": [
              {
                "mqtt": "ON",
                "type": "value",
                "google": true
              },
              {
                "mqtt": "OFF",
                "type": "value",
                "google": false
              }
            ]
          }
        }
      }
    ],
    "customData": null
  },
  "bedroom/airFreshener": {
    "id": "bedroom/airFreshener",
    "type": "action.devices.types.AIRFRESHENER",
    "disabled": false,
    "willReportState": true,
    "roomHint": "Bedroom",
    "name": {
      "defaultNames": [],
      "name": "Air freshener",
      "nicknames": []
    },
    "deviceInfo": {
      "manufacturer": "HomeAutio",
      "model": "DIY",
      "hwVersion": "1.0",
      "swVersion": "1.0"
    },
    "traits": [
      {
        "trait": "action.devices.traits.OnOff",
        "attributes": {},
        "commands": {
          "action.devices.commands.OnOff": {
            "on": "cmnd/tasmota_2/POWER"
          }
        },
        "state": {
          "on": {
            "topic": "cmnd/tasmota_2/POWER",
            "googleType": "bool",
            "valueMap": [
              {
                "mqtt": "on",
                "type": "value",
                "google": true
              },
              {
                "mqtt": "off",
                "type": "value",
                "google": false
              }
            ]
          }
        }
      },
      {
        "trait": "action.devices.traits.Modes",
        "attributes": {
          "availableModes": [
            {
              "name": "input source",
              "name_values": [
                {
                  "name_synonym": [
                    "activity"
                  ],
                  "lang": "en"
                }
              ],
              "settings": [
                {
                  "setting_name": "tv",
                  "setting_values": [
                    {
                      "setting_synonym": [
                        "tv",
                        "television"
                      ],
                      "lang": "en"
                    }
                  ]
                },
                {
                  "setting_name": "meda player",
                  "setting_values": [
                    {
                      "setting_synonym": [
                        "chromecast"
                      ],
                      "lang": "en"
                    }
                  ]
                }
              ],
              "ordered": false
            }
          ]
        },
        "commands": {
          "action.devices.commands.SetModes": {
            "updateModeSettings.input source": "MQTT_COMMAND_TOPIC"
          }
        },
        "state": {
          "currentModeSettings.input source": {
            "topic": "MQTT_STATE_TOPIC",
            "googleType": "string",
            "valueMap": [
              {
                "mqtt": "Watch TV",
                "type": "value",
                "google": "tv"
              },
              {
                "mqtt": "Watch Chromecast",
                "type": "value",
                "google": "media player"
              },
              {
                "mqtt": "Watch Roku",
                "type": "value",
                "google": "game console"
              },
              {
                "mqtt": "PowerOff",
                "type": "value",
                "google": "off"
              }
            ]
          }
        }
      }
    ],
    "customData": null
  },
  "livingroom/thermostat": {
    "id": "livingroom/thermostat",
    "type": "action.devices.types.THERMOSTAT",
    "disabled": false,
    "willReportState": true,
    "roomHint": "Living room",
    "name": {
      "defaultNames": [],
      "name": "Thermostat [Living room]",
      "nicknames": []
    },
    "deviceInfo": null,
    "traits": [
      {
        "trait": "action.devices.traits.TemperatureSetting",
        "attributes": {
          "availableThermostatModes": "off,heat,cool,on,heatcool,auto,fan-only,purifier,eco,dry",
          "thermostatTemperatureUnit": "C"
        },
        "commands": {
          "action.devices.commands.ThermostatTemperatureSetpoint": {
            "thermostatTemperatureSetpoint": "livingroom/thermostat/thermostatTemperatureSetpoint/set"
          },
          "action.devices.commands.ThermostatTemperatureSetRange": {
            "thermostatTemperatureSetpointHigh": "livingroom/thermostat/thermostatTemperatureSetpointHigh/set",
            "thermostatTemperatureSetpointLow": "livingroom/thermostat/thermostatTemperatureSetpointLow/set"
          },
          "action.devices.commands.ThermostatSetMode": {
            "thermostatMode": "livingroom/thermostat/thermostatMode/set"
          },
          "action.devices.commands.TemperatureRelative": {
            "thermostatTemperatureRelativeDegree": "livingroom/thermostat/thermostatTemperatureRelativeDegree/set",
            "thermostatTemperatureRelativeWeight": "livingroom/thermostat/thermostatTemperatureRelativeWeight/set"
          }
        },
        "state": {
          "thermostatMode": {
            "topic": "livingroom/thermostat/thermostatMode",
            "googleType": "string",
            "valueMap": []
          },
          "thermostatTemperatureSetpoint": {
            "topic": "livingroom/thermostat/thermostatTemperatureSetpoint",
            "googleType": "numeric",
            "valueMap": null
          },
          "thermostatTemperatureAmbient": {
            "topic": "livingroom/thermostat/thermostatTemperatureAmbient",
            "googleType": "numeric",
            "valueMap": null
          },
          "thermostatTemperatureSetpointHigh": {
            "topic": "livingroom/thermostat/thermostatTemperatureSetpointHigh",
            "googleType": "numeric",
            "valueMap": null
          },
          "thermostatTemperatureSetpointLow": {
            "topic": "livingroom/thermostat/thermostatTemperatureSetpointLow",
            "googleType": "numeric",
            "valueMap": null
          },
          "thermostatHumidityAmbient": {
            "topic": "livingroom/thermostat/thermostatHumidityAmbient",
            "googleType": "numeric",
            "valueMap": null
          }
        }
      }
    ],
    "customData": null
  },
  "securitySystem": {
    "id": "securitySystem",
    "type": "action.devices.types.SECURITYSYSTEM",
    "disabled": false,
    "willReportState": true,
    "roomHint": "Living room",
    "name": {
      "defaultNames": [],
      "name": "Security system",
      "nicknames": []
    },
    "deviceInfo": {
      "manufacturer": "openHome",
      "model": "0",
      "hwVersion": "0",
      "swVersion": "0"
    },
    "traits": [
      {
        "trait": "action.devices.traits.ArmDisarm",
        "attributes": {
          "availableArmLevels": {
            "levels": [
              {
                "level_name": "Disarmed",
                "level_values": [
                  {
                    "level_synonym": [
                      "no security",
                      "level 0",
                      "SL0",
                      "disarmed"
                    ],
                    "lang": "en"
                  }
                ]
              },
              {
                "level_name": "Armed-shell",
                "level_values": [
                  {
                    "level_synonym": [
                      "low security",
                      "shell",
                      "level 1",
                      "SL1"
                    ],
                    "lang": "en"
                  }
                ]
              },
              {
                "level_name": "Armed-night",
                "level_values": [
                  {
                    "level_synonym": [
                      "medium security",
                      "night",
                      "level 2",
                      "SL2",
                      "sleep"
                    ],
                    "lang": "en"
                  }
                ]
              },
              {
                "level_name": "Armed-away",
                "level_values": [
                  {
                    "level_synonym": [
                      "high security",
                      "away",
                      "level 3",
                      "SL3"
                    ],
                    "lang": "en"
                  }
                ]
              }
            ],
            "ordered": false
          }
        },
        "commands": {
          "action.devices.commands.ArmDisarm": {
            "arm": "securitySystem/arm/set",
            "cancel": "securitySystem/cancel/set",
            "armLevel": "securitySystem/armLevel/set"
          }
        },
        "state": {
          "isArmed": {
            "topic": "securitySystem/isArmed",
            "googleType": "bool",
            "valueMap": null
          },
          "currentArmLevel": {
            "topic": "securitySystem/armLevel",
            "googleType": "string",
            "valueMap": []
          },
          "exitAllowance": {
            "topic": "securitySystem/exitAllowance",
            "googleType": "numeric",
            "valueMap": null
          }
        }
      },
      {
        "trait": "action.devices.traits.StatusReport",
        "attributes": {},
        "commands": {},
        "state": {
          "currentStatusReport.[0].blocking": {
            "topic": "securitySystem/blocking",
            "googleType": "bool",
            "valueMap": null
          },
          "currentStatusReport.[0].deviceTarget": {
            "topic": "securitySystem/deviceTarget",
            "googleType": "string",
            "valueMap": []
          },
          "currentStatusReport.[0].priority": {
            "topic": "securitySystem/priority",
            "googleType": "numeric",
            "valueMap": null
          },
          "currentStatusReport.[0].statusCode": {
            "topic": "securitySystem/statusCode",
            "googleType": "string",
            "valueMap": []
          }
        }
      }
    ],
    "customData": null
  },
  "livingroom/amplifier": {
    "id": "livingroom/amplifier",
    "type": "action.devices.types.AUDIO_VIDEO_RECEIVER",
    "disabled": false,
    "willReportState": true,
    "roomHint": "Living room",
    "name": {
      "defaultNames": [],
      "name": "Amplifier",
      "nicknames": []
    },
    "deviceInfo": null,
    "traits": [
      {
        "trait": "action.devices.traits.InputSelector",
        "attributes": {
          "availableInputs": [
            {
              "key": "MPLAY",
              "names": [
                {
                  "lang": "en",
                  "name_synonym": [
                    "hdmi 1",
                    "1st hdmi",
                    "kodi"
                  ]
                }
              ]
            },
            {
              "key": "AUX1",
              "names": [
                {
                  "lang": "en",
                  "name_synonym": [
                    "aux 1",
                    "audio"
                  ]
                }
              ]
            }
          ],
          "orderedInputs": true
        },
        "commands": {
          "action.devices.commands.SetInput": {
            "newInput": "livingroom/amplifier/input/set"
          }
        },
        "state": {
          "currentInput": {
            "topic": "livingroom/amplifier/input",
            "googleType": "string",
            "valueMap": null
          }
        }
      }
    ],
    "customData": null
  },
  "livingroom/airFreshener": {
    "id": "livingroom/airFreshener",
    "type": "action.devices.types.AIRFRESHENER",
    "disabled": false,
    "willReportState": true,
    "roomHint": "Living room",
    "name": {
      "defaultNames": [],
      "name": "Air freshener",
      "nicknames": []
    },
    "deviceInfo": {
      "manufacturer": "HomeAutio",
      "model": "DIY",
      "hwVersion": "1.0",
      "swVersion": "1.0"
    },
    "traits": [
      {
        "trait": "action.devices.traits.OnOff",
        "attributes": null,
        "commands": {
          "action.devices.commands.OnOff": {
            "on": "livingroom/airFreshener/power/set"
          }
        },
        "state": {
          "on": {
            "topic": "livingroom/airFreshener/power",
            "googleType": "bool",
            "valueMap": [
              {
                "mqtt": "on",
                "type": "value",
                "google": true
              },
              {
                "mqtt": "off",
                "type": "value",
                "google": false
              }
            ]
          }
        }
      },
      {
        "trait": "action.devices.traits.Modes",
        "attributes": {
          "availableModes": [
            {
              "name": "input source",
              "name_values": [
                {
                  "name_synonym": [
                    "activity"
                  ],
                  "lang": "en"
                }
              ],
              "settings": [
                {
                  "setting_name": "tv",
                  "setting_values": [
                    {
                      "setting_synonym": [
                        "tv",
                        "television"
                      ],
                      "lang": "en"
                    }
                  ]
                },
                {
                  "setting_name": "meda player",
                  "setting_values": [
                    {
                      "setting_synonym": [
                        "chromecast"
                      ],
                      "lang": "en"
                    }
                  ]
                }
              ],
              "ordered": false
            }
          ]
        },
        "commands": {
          "action.devices.commands.SetModes": {
            "updateModeSettings.input source": "livingroom/airFreshener/mode/set"
          }
        },
        "state": {
          "currentModeSettings.input source": {
            "topic": "livingroom/airFreshener/mode",
            "googleType": "string",
            "valueMap": [
              {
                "mqtt": "Watch TV",
                "type": "value",
                "google": "tv"
              },
              {
                "mqtt": "Watch Chromecast",
                "type": "value",
                "google": "media player"
              },
              {
                "mqtt": "Watch Roku",
                "type": "value",
                "google": "game console"
              },
              {
                "mqtt": "PowerOff",
                "type": "value",
                "google": "off"
              }
            ]
          }
        }
      }
    ],
    "customData": null
  },
  "hall/mainDoor": {
    "id": "hall/mainDoor",
    "type": "action.devices.types.DOOR",
    "disabled": false,
    "willReportState": true,
    "roomHint": "Hall",
    "name": {
      "defaultNames": [],
      "name": "Main door",
      "nicknames": []
    },
    "deviceInfo": null,
    "traits": [
      {
        "trait": "action.devices.traits.OpenClose",
        "attributes": {
          "openDirection": [
            "LEFT",
            "RIGHT"
          ],
          "discreteOnlyOpenClose": true,
          "queryOnlyOpenClose": true
        },
        "commands": {},
        "state": {
          "openPercent": {
            "topic": "hall/mainDoor/status",
            "googleType": "numeric",
            "valueMap": [
              {
                "mqtt": "OPEN",
                "type": "value",
                "google": 100
              },
              {
                "mqtt": "CLOSED",
                "type": "value",
                "google": 0
              }
            ]
          }
        }
      }
    ],
    "customData": null
  },
  "kitchen/smokeDetector": {
    "id": "kitchen/smokeDetector",
    "type": "action.devices.types.SMOKE_DETECTOR",
    "disabled": false,
    "willReportState": true,
    "roomHint": "Kitchen",
    "name": {
      "defaultNames": [],
      "name": "Smoke sensor",
      "nicknames": []
    },
    "deviceInfo": null,
    "traits": [
      {
        "trait": "action.devices.traits.SensorState",
        "attributes": {
          "sensorStatesSupported": [
            {
              "name": "SmokeLevel",
              "numericCapabilities": {
                "rawValueUnit": "PARTS_PER_MILLION"
              },
              "descriptiveCapabilities": {
                "availableStates": [
                  "smoke detected",
                  "no smoke detected"
                ]
              }
            }
          ]
        },
        "commands": {},
        "state": {
          "currentSensorStateData.[0].name": {
            "topic": null,
            "googleType": "string",
            "valueMap": [
              {
                "type": "static",
                "google": "SmokeLevel"
              }
            ]
          },
          "currentSensorStateData.[0].currentSensorState": {
            "topic": "kitchen/smokeDetector/sensorState",
            "googleType": "string",
            "valueMap": []
          }
        }
      }
    ],
    "customData": null
  },
  "bedroom/ac": {
    "id": "bedroom/ac",
    "type": "action.devices.types.AC_UNIT",
    "disabled": false,
    "willReportState": true,
    "roomHint": "Bedroom",
    "name": {
      "defaultNames": [],
      "name": "Air conditioning",
      "nicknames": []
    },
    "deviceInfo": null,
    "traits": [
      {
        "trait": "action.devices.traits.OnOff",
        "attributes": null,
        "commands": {
          "action.devices.commands.OnOff": {
            "on": "MQTT_COMMAND_TOPIC"
          }
        },
        "state": {
          "on": {
            "topic": "MQTT_STATE_TOPIC",
            "googleType": "bool",
            "valueMap": [
              {
                "mqtt": "on",
                "type": "value",
                "google": true
              },
              {
                "mqtt": "off",
                "type": "value",
                "google": false
              }
            ]
          }
        }
      },
      {
        "trait": "action.devices.traits.TemperatureSetting",
        "attributes": {
          "availableThermostatModes": "off,heat,cool,on",
          "thermostatTemperatureUnit": "C",
          "commandOnlyTemperatureSetting": true
        },
        "commands": {
          "action.devices.commands.ThermostatTemperatureSetpoint": {
            "thermostatTemperatureSetpoint": "MQTT_COMMAND_TOPIC"
          },
          "action.devices.commands.ThermostatTemperatureSetRange": {
            "thermostatTemperatureSetpointHigh": "MQTT_COMMAND_TOPIC",
            "thermostatTemperatureSetpointLow": "MQTT_COMMAND_TOPIC"
          },
          "action.devices.commands.ThermostatSetMode": {
            "thermostatMode": "MQTT_COMMAND_TOPIC"
          }
        },
        "state": {}
      },
      {
        "trait": "action.devices.traits.FanSpeed",
        "attributes": {
          "availableFanSpeeds": {
            "speeds": [
              {
                "speed_name": "Low",
                "speed_values": [
                  {
                    "speed_synonym": [
                      "low"
                    ],
                    "lang": "en"
                  }
                ]
              },
              {
                "speed_name": "High",
                "speed_values": [
                  {
                    "speed_synonym": [
                      "high"
                    ],
                    "lang": "en"
                  }
                ]
              }
            ],
            "ordered": true
          },
          "reversible": false
        },
        "commands": {
          "action.devices.commands.SetFanSpeed": {
            "fanSpeed": "MQTT_COMMAND_TOPIC"
          }
        },
        "state": {
          "currentFanSpeedSetting": {
            "topic": "MQTT_STATE_TOPIC",
            "googleType": "string",
            "valueMap": [
              {
                "mqtt": "1",
                "type": "value",
                "google": "Low"
              },
              {
                "mqtt": "4",
                "type": "value",
                "google": "High"
              }
            ]
          }
        }
      }
    ],
    "customData": null
  }
}